media/_Sounddevice.py
media/__init__.py
media/_ffmpeg.py
media/audio.py
media/exception.py
media/lib.py
media/picture.py
media/video.py
tkmedia-0.1.2.dist-info/LICENSE
tkmedia-0.1.2.dist-info/METADATA
tkmedia-0.1.2.dist-info/WHEEL
tkmedia-0.1.2.dist-info/top_level.txt
tkmedia-0.1.2.dist-info/RECORD
