Metadata-Version: 2.1
Name: tkmedia
Version: 0.1.2
Summary: Tkinter Media Support.
Home-page: https://github.com/Marusoftware/tkmedia3
Author: Marusoftware
Author-email: marusoftware@outlook.jp
License: MIT
Project-URL: Bug Tracker, https://github.com/Marusoftware/tkmedia3/issues
Project-URL: Documents, https://marusoftware.github.io/tkmedia3/
Keywords: tkmedia
Platform: UNKNOWN
Classifier: Development Status :: 4 - Beta
Classifier: Programming Language :: Python
Classifier: Programming Language :: Python :: 3
Requires-Python: >=3.8
License-File: LICENSE
Requires-Dist: av
Requires-Dist: numpy
Requires-Dist: Pillow
Requires-Dist: sounddevice
